HSS/HSS.py
HSS/Request_HSSAPI.py
HSS/__init__.py
HSS/apiurl_lists.py
HSS/errors.py
HSS.py-1.2.1.dist-info/METADATA
HSS.py-1.2.1.dist-info/WHEEL
HSS.py-1.2.1.dist-info/top_level.txt
HSS.py-1.2.1.dist-info/RECORD
