Metadata-Version: 2.1
Name: HSS.py
Version: 1.2.1
Summary: Easy to use HSS API.
Home-page: https://github.com/HSS-Project/HSS.py
Author: HSS-Project
Author-email: kazuma1112@munesky.net
License: MIT
Keywords: HSS Schedule School
Classifier: License :: OSI Approved :: MIT License
Classifier: Programming Language :: Python :: 3.10
Requires-Dist: requests
